proxy_spinner/__init__.py
proxy_spinner/constants.py
proxy_spinner/proxy_spinner.py
proxy_spinner-0.5.dist-info/LICENSE
proxy_spinner-0.5.dist-info/METADATA
proxy_spinner-0.5.dist-info/WHEEL
proxy_spinner-0.5.dist-info/top_level.txt
proxy_spinner-0.5.dist-info/RECORD
