Metadata-Version: 2.1
Name: proxy-spinner
Version: 0.5
Summary: ProxySpinner is an straightforward, non-reliable, non-secure, but easy-to-use library for avoiding IP blocking by rotating free proxies on demand. It relies in services like proxyscrape.com to get the proxies and rotates them on demand, and is subject to the availability of that service and the proxies it lists.
Home-page: https://github.com/Eric-Canas/proxy-spinner
Author: Eric-Canas
Author-email: eric@ericcanas.com
License: MIT
Classifier: Development Status :: 4 - Beta
Classifier: License :: OSI Approved :: MIT License
Classifier: Programming Language :: Python
Classifier: Programming Language :: Python :: 3
Classifier: Operating System :: OS Independent
Classifier: Intended Audience :: Developers
Classifier: Topic :: System :: Networking
Classifier: Topic :: Software Development :: Libraries
Classifier: Topic :: Software Development :: Libraries :: Python Modules
Classifier: Topic :: Utilities
Requires-Python: >=3.6
License-File: LICENSE
Requires-Dist: requests
Requires-Dist: loguru
